infi.locking-0.1.3-py2.7-nspkg.pth
infi/locking/__init__.py
infi/locking/__version__.py
infi.locking-0.1.3.dist-info/METADATA
infi.locking-0.1.3.dist-info/WHEEL
infi.locking-0.1.3.dist-info/entry_points.txt
infi.locking-0.1.3.dist-info/namespace_packages.txt
infi.locking-0.1.3.dist-info/top_level.txt
infi.locking-0.1.3.dist-info/RECORD
